LICENSE
MANIFEST.in
README.md
setup.py
gibson_env_utilities/__init__.py
gibson_env_utilities/__version__.py
gibson_env_utilities/gibson_assets_utilities.py
gibson_env_utilities/gibson_environments_data.py
gibson_env_utilities/gibson_run_config.py
gibson_env_utilities/voronoi_graph_generator.py
gibson_env_utilities.egg-info/PKG-INFO
gibson_env_utilities.egg-info/SOURCES.txt
gibson_env_utilities.egg-info/dependency_links.txt
gibson_env_utilities.egg-info/entry_points.txt
gibson_env_utilities.egg-info/requires.txt
gibson_env_utilities.egg-info/top_level.txt
gibson_env_utilities/data/environments_data.yaml
gibson_env_utilities/data/gibson_config_file.yaml
gibson_env_utilities/data/matterport_semantic_labels.tsv
gibson_env_utilities/data/maps/area2_floor_0.png
gibson_env_utilities/data/maps/area2_floor_1.png
gibson_env_utilities/data/maps/area3_floor_0.png
gibson_env_utilities/data/maps/area4_floor_0.png
gibson_env_utilities/data/maps/area5_2_floor_0.png
gibson_env_utilities/data/maps/area5_floor_0.png
gibson_env_utilities/data/maps/area6_floor_0.png
gibson_env_utilities/data/maps/house10_floor_0.png
gibson_env_utilities/data/maps/house10_floor_1.png
gibson_env_utilities/data/maps/house10_floor_2.png
gibson_env_utilities/data/maps/house11_floor_0.png
gibson_env_utilities/data/maps/house11_floor_1.png
gibson_env_utilities/data/maps/house11_floor_2.png
gibson_env_utilities/data/maps/house12_floor_0.png
gibson_env_utilities/data/maps/house13_floor_0.png
gibson_env_utilities/data/maps/house13_floor_1.png
gibson_env_utilities/data/maps/house13_floor_2.png
gibson_env_utilities/data/maps/house13_floor_3.png
gibson_env_utilities/data/maps/house14_floor_0.png
gibson_env_utilities/data/maps/house15_floor_0.png
gibson_env_utilities/data/maps/house15_floor_1.png
gibson_env_utilities/data/maps/house15_floor_2.png
gibson_env_utilities/data/maps/house15_floor_3.png
gibson_env_utilities/data/maps/house15_floor_4.png
gibson_env_utilities/data/maps/house16_floor_0.png
gibson_env_utilities/data/maps/house16_floor_1.png
gibson_env_utilities/data/maps/house17_floor_0.png
gibson_env_utilities/data/maps/house18_floor_0.png
gibson_env_utilities/data/maps/house18_floor_1.png
gibson_env_utilities/data/maps/house18_floor_2.png
