Metadata-Version: 2.1
Name: gibson-env-utilities
Version: 1.2.1
Summary: GibsonEnv utilities
Home-page: https://github.com/micheleantonazzi/gibson-env-utilities
Author: Michele Antonazzi
Author-email: micheleantonazzi@gmail.com
License: Apache Licence 2.0
Platform: UNKNOWN
Classifier: License :: OSI Approved :: Apache Software License
Classifier: Programming Language :: Python :: 3
Provides-Extra: test
